jpostcode
