Metadata-Version: 1.0
Name: jpostcode-python
Version: 0.0.6
Summary: Japanese postcode utils
Home-page: https://github.com/uehara1414/jpostcode-python
Author: uehara1414
Author-email: akiya.noface@gmail.com
License: UNKNOWN
Platform: UNKNOWN
